exenworldgen/__init__.py
exenworldgen/__main__.py
exenworldgen/_types.py
exenworldgen/utils.py
exenworldgen/worldgen.py
exenworldgen-1.0.dist-info/METADATA
exenworldgen-1.0.dist-info/LICENSE
exenworldgen-1.0.dist-info/WHEEL
exenworldgen-1.0.dist-info/RECORD
