Metadata-Version: 2.1
Name: exenworldgen
Version: 1.0
Summary: Cool world generator
Home-page: https://github.com/Exenifix/worldgen
License: MIT
Author: Exenifix
Requires-Python: >=3.10,<4.0
Classifier: License :: OSI Approved :: MIT License
Classifier: Programming Language :: Python :: 3
Classifier: Programming Language :: Python :: 3.10
Classifier: Programming Language :: Python :: 3.11
Requires-Dist: exencolor (>=1.0,<2.0)
Project-URL: Repository, https://github.com/Exenifix/worldgen
